wirewalk/__init__.py
wirewalk/_modidx.py
wirewalk/core.py
wirewalk-0.0.3.dist-info/LICENSE
wirewalk-0.0.3.dist-info/METADATA
wirewalk-0.0.3.dist-info/WHEEL
wirewalk-0.0.3.dist-info/entry_points.txt
wirewalk-0.0.3.dist-info/top_level.txt
wirewalk-0.0.3.dist-info/RECORD
