Metadata-Version: 2.1
Name: wirewalk
Version: 0.0.3
Summary: Python3 Implementation of the WireWalk Algorithm
Home-page: https://github.com/TesfaAsmara/wirewalk
Author: tesfaasmara
Author-email: 57428343+TesfaAsmara@users.noreply.github.com
License: Apache Software License 2.0
Keywords: nbdev jupyter notebook python
Classifier: Development Status :: 4 - Beta
Classifier: Intended Audience :: Developers
Classifier: Natural Language :: English
Classifier: Programming Language :: Python :: 3.7
Classifier: Programming Language :: Python :: 3.8
Classifier: Programming Language :: Python :: 3.9
Classifier: Programming Language :: Python :: 3.10
Classifier: License :: OSI Approved :: Apache Software License
Requires-Python: >=3.7
License-File: LICENSE
Requires-Dist: networkx
Requires-Dist: numpy
Requires-Dist: gensim
Requires-Dist: editdistance
Provides-Extra: dev
